comathon/Real_time_003_cmt.py
comathon/Real_time_003_cmt_jk.py
comathon/Real_time_CS_bot_cmt.py
comathon/__init__.py
comathon/cmt_exchange.py
comathon/cmt_quotation.py
comathon/cmt_test.py
comathon/cmt_test_obsolete.py
comathon/cmt_trading_v001.py
comathon/comathon_template.py
comathon/comathon_testrun_YD.py
comathon/comathon_testrun_YD2.py
comathon/test_algo.py
comathon/test_algo_python_0821.py
comathon_test/__init__.py
comathon_test/test_myfunctions.py
comathon-0.0.46.dist-info/LICENSE.rst
comathon-0.0.46.dist-info/METADATA
comathon-0.0.46.dist-info/WHEEL
comathon-0.0.46.dist-info/top_level.txt
comathon-0.0.46.dist-info/RECORD
